showme-tree/__init__.py
showme-tree/main.py
showme_tree/__init__.py
showme_tree/main.py
showme_tree-1.0.7.dist-info/LICENSE
showme_tree-1.0.7.dist-info/METADATA
showme_tree-1.0.7.dist-info/WHEEL
showme_tree-1.0.7.dist-info/entry_points.txt
showme_tree-1.0.7.dist-info/top_level.txt
showme_tree-1.0.7.dist-info/RECORD
