Metadata-Version: 2.1
Name: showme-tree
Version: 1.0.7
Summary: A command-line tool that prints the folder and file structure of your VSCode project, excluding nested items of content in .gitignore.
Home-page: https://github.com/sshovkov/showme-folder-structure
Author: Sophia Shovkovy
License: UNKNOWN
Platform: UNKNOWN
License-File: LICENSE
Requires-Dist: gitignore-parser
